staticon/__init__.py
staticon-0.0.6.dist-info/LICENSE
staticon-0.0.6.dist-info/METADATA
staticon-0.0.6.dist-info/WHEEL
staticon-0.0.6.dist-info/top_level.txt
staticon-0.0.6.dist-info/RECORD
