Metadata-Version: 2.1
Name: staticon
Version: 0.0.6
Summary: A python library for printing pretty status messages
Home-page: https://github.com/nathansmerrill/staticon
Author: Nathan Merrill
Author-email: mathiscool3000@gmail.com
License: UNKNOWN
Platform: UNKNOWN
Classifier: Programming Language :: Python :: 3
Classifier: Operating System :: OS Independent
Requires-Python: >=3.6
